oc_ldap_client/__init__.py
oc_ldap_client/oc_ldap.py
oc_ldap_client/oc_ldap_objects.py
oc_ldap_client-1.1.1.dist-info/LICENSE
oc_ldap_client-1.1.1.dist-info/METADATA
oc_ldap_client-1.1.1.dist-info/WHEEL
oc_ldap_client-1.1.1.dist-info/top_level.txt
oc_ldap_client-1.1.1.dist-info/RECORD
