Metadata-Version: 2.1
Name: oc-ldap-client
Version: 1.1.1
Summary: Base classes for LDAP objects
License: LGPLv2
Requires-Python: >=3.6
License-File: LICENSE
Requires-Dist: ldap3
Requires-Dist: fs
Requires-Dist: urllib3
